dicom2fem/__init__.py
dicom2fem/dicom2fem.py
dicom2fem/genfem_base.py
dicom2fem/marching_cubes.py
dicom2fem/seg2fem.py
dicom2fem/viewer.py
dicom2fem/png/brain.png
dicom2fem-2.1.1.dist-info/licenses/LICENSE
dicom2fem-2.1.1.dist-info/METADATA
dicom2fem-2.1.1.dist-info/WHEEL
dicom2fem-2.1.1.dist-info/entry_points.txt
dicom2fem-2.1.1.dist-info/top_level.txt
dicom2fem-2.1.1.dist-info/RECORD
