Metadata-Version: 2.4
Name: dicom2fem
Version: 2.1.1
Summary: Generation of finite element meshes from DICOM images
Author-email: Vladimír Lukeš <vlukes@kme.zcu.cz>
Project-URL: homepage, https://github.com/vlukes/dicom2fem
Keywords: fem,dicom
Classifier: Development Status :: 4 - Beta
Classifier: Intended Audience :: Developers
Classifier: Topic :: Scientific/Engineering :: Bio-Informatics
Classifier: Programming Language :: Python :: 3
Classifier: Operating System :: OS Independent
Requires-Python: >=3.10
License-File: LICENSE
Requires-Dist: numpy
Requires-Dist: scipy
Requires-Dist: scikit-learn
Requires-Dist: pyvista
Requires-Dist: io3d
Requires-Dist: loguru
Requires-Dist: imma
Requires-Dist: imcut
Requires-Dist: pygco
Requires-Dist: seededitorqt
Requires-Dist: pydicom<3.0.0,>=2.0.0
Dynamic: license-file
